setup.py
zfx_autochrome/UTF8编码.py
zfx_autochrome/UTF8解码.py
zfx_autochrome/__init__.py
zfx_autochrome/totp_生成验证码.py
zfx_autochrome/关闭当前标签页.py
zfx_autochrome/关闭浏览器.py
zfx_autochrome/切换标签页.py
zfx_autochrome/初始化_普通模式.py
zfx_autochrome/初始化_禁用图片.py
zfx_autochrome/删除元素.py
zfx_autochrome/删除所有Cookies.py
zfx_autochrome/判断页面是否加载完毕.py
zfx_autochrome/刷新页面.py
zfx_autochrome/取当前页面标题.py
zfx_autochrome/取当前页面网址.py
zfx_autochrome/取网页源码.py
zfx_autochrome/截图并保存.py
zfx_autochrome/新建空白页.py
zfx_autochrome/滚动到元素所在处.py
zfx_autochrome/滚动到页面底部.py
zfx_autochrome/滚动指定像素.py
zfx_autochrome/点击元素.py
zfx_autochrome/生成随机ChromeUA.py
zfx_autochrome/等待元素出现.py
zfx_autochrome/等待元素可点击.py
zfx_autochrome/等待元素可点击_快速.py
zfx_autochrome/等待元素可见.py
zfx_autochrome/获取Cookies.py
zfx_autochrome/访问网页.py
zfx_autochrome/输入文本.py
zfx_autochrome/隐藏滚动条.py
zfx_autochrome.egg-info/PKG-INFO
zfx_autochrome.egg-info/SOURCES.txt
zfx_autochrome.egg-info/dependency_links.txt
zfx_autochrome.egg-info/requires.txt
zfx_autochrome.egg-info/top_level.txt