Metadata-Version: 2.1
Name: zfx_autochrome
Version: 1.0.18
Summary: 这是一个用于谷歌浏览器网页自动化的库,欢迎各路大神反馈意见及提出需求。企鹅号：424491679,企鹅群：961483644
Home-page: 
Author: zengfengxiang
Author-email: 424491679@qq.com
Requires-Dist: selenium
Requires-Dist: pyotp
